MANIFEST.in
README.md
requirements-dev.txt
requirements.txt
setup.py
django_master_linter.egg-info/PKG-INFO
django_master_linter.egg-info/SOURCES.txt
django_master_linter.egg-info/dependency_links.txt
django_master_linter.egg-info/not-zip-safe
django_master_linter.egg-info/requires.txt
django_master_linter.egg-info/top_level.txt
djangomaster_linter/__init__.py
djangomaster_linter/tests.py
djangomaster_linter/version.txt
djangomaster_linter/master/__init__.py
djangomaster_linter/master/base.py
djangomaster_linter/templates/djangomaster_linter/base.html