Metadata-Version: 1.0
Name: django-master-linter
Version: 0.0.7
Summary: django master linter
Home-page: http://pypi.python.org/pypi/django-master-linter/
Author: Andre Farzat
Author-email: andrefarzat@gmail.com
License: LICENSE
Platform: UNKNOWN
